newspaper3k_haystack/__init__.py
newspaper3k_haystack/newspaper3k_haystack.py
newspaper3k_haystack-0.1.1.dist-info/LICENSE.txt
newspaper3k_haystack-0.1.1.dist-info/METADATA
newspaper3k_haystack-0.1.1.dist-info/WHEEL
newspaper3k_haystack-0.1.1.dist-info/top_level.txt
newspaper3k_haystack-0.1.1.dist-info/RECORD
