Metadata-Version: 2.1
Name: newspaper3k-haystack
Version: 0.1.1
Summary: A simple newspaper3k haystack node wrapper. A node for scraping articles given a link and a crawler.
Home-page: https://github.com/Haradai/newspaper3k_haystack
Author: Josep Maria Rocafort
Author-email: josem.rocafortf@gmail.com
Project-URL: Bug Tracker, https://github.com/Haradai/newspaper3k_haystack/issues
Classifier: Programming Language :: Python :: 3
Classifier: License :: OSI Approved :: MIT License
Classifier: Operating System :: OS Independent
Requires-Python: >=3.6
License-File: LICENSE.txt
Requires-Dist: newspaper3k
Requires-Dist: beautifulsoup4
Requires-Dist: tqdm
Requires-Dist: farm-haystack
